scanoss/__init__.py
scanoss/binary.py
scanoss/client.py
scanoss/bin/.gitkeep
scanoss/bin/scanoss
scanoss/v1/commands_pb2.py
scanoss/v1/enums_pb2.py
scanoss/v1/types_pb2.py
scanoss_test-2.0.12.dist-info/METADATA
scanoss_test-2.0.12.dist-info/WHEEL
scanoss_test-2.0.12.dist-info/top_level.txt
scanoss_test-2.0.12.dist-info/RECORD
